[
  {
    "chunk_id": "28d8d807-f4a2-4f25-819b-149475241aeb",
    "heading": "",
    "text": "f. promoting multifunctional, diverse and inclusive leisure and cultural venues and promoting associated uses; BACK TO POLICIES g. promoting and focusing markets in town centres and recognising their role in adding variety, promoting local enterprise and contributing to local character; h. supporting meanwhile and community uses where they help to activate and revitalise vacant town centre units and sites; and i. prioritising street level activity along the borough’s primary and secondary frontages and key pedestrian routes to encourage opportunities for social interaction. 2. The council will expect development proposals to support the town centre hierarchy and to maintain and enhance the role and function of the town centres: 254 Tower Hamlets Local Plan BACK TO POLICIES Table 11: Town Centre Hierarchy TOWN CENTRES",
    "tokens": 124,
    "source": "f985ddd124245046f2e5c67c656bba2e_TH_Local_Plan_2024_UPDATE_(ONLINE-HIGH_RES)"
  }
]