[
  {
    "chunk_id": "738a3c8b-93d3-45fa-a666-0fe2ffb395ff",
    "heading": "",
    "text": "6. Development proposals for new residential and commercial moorings on waterways should include an electrical hook-up at each mooring point; where demonstrated that this is not possible, other clean energy alternatives such as solar panels must be considered. Tower Hamlets Local Plan 137 CLEAN AND GREEN FUTURE Figure 8: Air quality map BACK TO POLICIES 138 Tower Hamlets Local Plan BACK TO POLICIES Supporting text 13.112 The borough is committed to reducing the exposure to poor air quality within Tower Hamlets. Levels of nitrogen dioxide and particulates (PM10 and PM2.5) are of particular concern, due to their impacts on human health [21] . Air pollution is associated with a number of adverse health impacts, which more acutely affect the most vulnerable in society, particularly children, older people, and individuals with heart and lung conditions..",
    "tokens": 136,
    "source": "f985ddd124245046f2e5c67c656bba2e_TH_Local_Plan_2024_UPDATE_(ONLINE-HIGH_RES)"
  }
]