[
  {
    "chunk_id": "4e6ef6d9-bbc4-40bd-a78c-0bf47ff74f55",
    "heading": "",
    "text": "Land uses, activities, and delivery z Development should consist of a mixed-use, residential-led scheme with some employment spaces. z Acceptable land uses include: – Residential (Class C3) – Town centre uses (Class E) – Community uses (Class F1/F2) z Required on-site infrastructure includes: – Community centre z The site is in multiple ownership, and landowners and developers should work together to develop a comprehensive design-led masterplan for redevelopment of this site, to ensure development is delivered sustainably. Effective engagement between landowners, developers and leaseholders will be needed to facilitate potential land assembly and comprehensive redevelopment.",
    "tokens": 95,
    "source": "f985ddd124245046f2e5c67c656bba2e_TH_Local_Plan_2024_UPDATE_(ONLINE-HIGH_RES)"
  }
]