[
  {
    "chunk_id": "1097f3d7-5c49-4a6a-9186-03e9b59e4370",
    "heading": "",
    "text": "CLEAN AND GREEN FUTURE 13. Clean and green future CG1 – Mitigating and adapting to a changing climate CG2 – Low energy buildings CG3 – Low carbon energy and heating CG4 – Embodied carbon, retrofit and the circular economy CG5 – Overheating CG6 – Managing flood risk CG7 – Sustainable drainage CG8 – Water efficient design CG9 – Air quality CG10 – Noise and vibration CG11 – Contaminated land 5 A Cleaner and Greener Future for Tower Hamlets (2023) 6 Tower Hamlets Net Zero Carbon Partnership Action Plan (2021) 7 The Climate Change Act 2008 (2050 Target Amendment) Order 2019 8 London Energy and Greenhouse Gas Inventory (LEGGI) (2020) BACK TO POLICIES Introduction",
    "tokens": 114,
    "source": "f985ddd124245046f2e5c67c656bba2e_TH_Local_Plan_2024_UPDATE_(ONLINE-HIGH_RES)"
  }
]