[
  {
    "chunk_id": "e18828e4-be9d-4e0e-b8f8-94eb5c391124",
    "heading": "",
    "text": "19.10 This policy seeks to manage growth to ensure it does not increase traffic congestion and crowding on public transport due to BACK TO POLICIES trip generation from developments and through-trips. The location of development proposals close to services and amenities, integration with the transport network, prioritising the most sustainable forms of travel, and facilitating and enabling behaviour towards the use of public transport and active forms of travel are crucial factors in accommodating the predicted population and economic changes over the plan period. Development proposals must accord with the latest guidance and policy approach set out in the London Plan, The Mayor of London’s Transport Strategy,the Tower Hamlets Transport Strategy (2019) and seek to achieve the targets of the most recent Local Implementation Plan (LIP). 346 Tower Hamlets Local Plan BACK TO POLICIES",
    "tokens": 135,
    "source": "f985ddd124245046f2e5c67c656bba2e_TH_Local_Plan_2024_UPDATE_(ONLINE-HIGH_RES)"
  }
]