[
  {
    "chunk_id": "0cc24b4b-8749-434c-b455-acaca42b66d4",
    "heading": "",
    "text": "18.21 The consolidation of open spaces increases their recreational and biodiversity values. Once the total area of new open space provided across development sites reaches 1ha, this can lead to a reduction in deficiency in access to open space. Locating public realm adjacent to water spaces also expands visual amenity, which is important for general well-being. To ensure new developments achieve these outcomes, development proposals must locate new open space in a manner that enables their expansion – either by situating them next to existing open space on adjacent sites, or in a location where further pieces of open space may be delivered on adjacent sites in future.",
    "tokens": 108,
    "source": "f985ddd124245046f2e5c67c656bba2e_TH_Local_Plan_2024_UPDATE_(ONLINE-HIGH_RES)"
  }
]