[
  {
    "chunk_id": "1a4831f7-6d94-49a9-8ee9-e18c48837cc6",
    "heading": "",
    "text": "DELIVERING THE LOCAL PLAN 11.60 Social value should be considered early in the development process and applicants should engage with the council’s development management and infrastructure planning teams. 11.61 Part 2(b) requires the social value strategy to demonstrate how the development proposal will support social inclusion, economic well-being, equal opportunity, and community cohesion throughout its lifecycle. To demonstrate this, the strategy should provide a structure as to how social value will be implemented through each stage of the proposal, setting-out clear goals and implementation strategies and outlining measurable targets to ensure effective monitoring, reporting, and assessment.",
    "tokens": 96,
    "source": "f985ddd124245046f2e5c67c656bba2e_TH_Local_Plan_2024_UPDATE_(ONLINE-HIGH_RES)"
  }
]