[
  {
    "chunk_id": "32b81abd-4bcc-4522-a33b-b5c9730b32bc",
    "heading": "",
    "text": "z providing sport and recreation opportunities; BIODIVERSITY AND OPEN SPACE z providing places to meet, play, socialise, and access community z activities and cultural events; z providing free and accessible spaces for children and young people, adult carers, and vulnerable and deprived people; z inclusive and supportive of mental health and well-being z helping to manage storm water drainage and flood risk; z mitigating the effects of climate change; z enhancing biodiversity; and z providing a cooling effect to reduce elevated urban air temperature.",
    "tokens": 84,
    "source": "f985ddd124245046f2e5c67c656bba2e_TH_Local_Plan_2024_UPDATE_(ONLINE-HIGH_RES)"
  }
]