[
  {
    "chunk_id": "6212a468-5134-4c3a-bcf2-a41698dc3455",
    "heading": "",
    "text": "INCLUSIVE ECONOMY AND GOOD GROWTH unrealistic. In such cases, the applicant should submit a report on the history and condition of the property to justify why marketing evidence should not be required and how and why reproviding employment space as part of redevelopment would not be viable. It should be demonstrated that the proposed development would not prejudice wider land-use objectives or the delivery of site allocations, and that reverse-sensitivity issues would not arise through conflict with surrounding existing uses, particularly where it lies within a cluster of other employment uses. The report should also demonstrate that the benefits of an alternative use would outweigh the benefits of the employment use to meet other local plan objectives, such as the need for complementary town centre uses or to maintain active frontages within town centres.",
    "tokens": 134,
    "source": "f985ddd124245046f2e5c67c656bba2e_TH_Local_Plan_2024_UPDATE_(ONLINE-HIGH_RES)"
  }
]