[
  {
    "chunk_id": "5481ace1-8687-4979-bec1-b920c76befce",
    "heading": "",
    "text": "13.88 Applicants are strongly encouraged to consider the requirements for SuDS at the earliest opportunity, as this will enable their more effective integration and provision. SuDS should also be considered alongside the ‘living building’ requirements outlined in Policy BO5, and green grid requirements outlined in Policy BO2, as SuDS can also have biodiversity and urban greening benefits. Applicants should demonstrate that they have considered different types of SuDS, prioritising SuDS which deliver multiple benefits, their ability to remove pollutants, their capacity, and future maintenance. 130 Tower Hamlets Local Plan BACK TO POLICIES",
    "tokens": 93,
    "source": "f985ddd124245046f2e5c67c656bba2e_TH_Local_Plan_2024_UPDATE_(ONLINE-HIGH_RES)"
  }
]