[
  {
    "chunk_id": "fe9a4fb9-a790-42fa-80b5-c8071536a99d",
    "heading": "",
    "text": "11.26 Part 2 of this policy requires major development proposals to complete and submit a rapid HIA, which should be undertaken using the council’s most current HIA guidance. Definition of what constitutes a major development proposal can be found in the glossary in Appendix 1. 11.27 Part 3 of this policy requires development proposals of a scale referrable to the GLA to complete and submit a detailed HIA, which should be undertaken using the council’s latest HIA guidance, and the scope of this assessment agreed with the council’s development management and public health services prior to commencement and at the earliest opportunity (part 3(a)). Definition of what constitutes a development proposal of a scale referrable to the GLA can be found in the glossary in appendix 1. A HIA can also be submitted as part of an Integrated Impact Assessment.",
    "tokens": 140,
    "source": "f985ddd124245046f2e5c67c656bba2e_TH_Local_Plan_2024_UPDATE_(ONLINE-HIGH_RES)"
  }
]